proyecto_mlops/__init__.py
proyecto_mlops/cli.py
proyecto_mlops/business_understanding/__init__.py
proyecto_mlops/data_preparation/__init__.py
proyecto_mlops/data_understanding/__init__.py
proyecto_mlops/deployment/__init__.py
proyecto_mlops/evaluation/__init__.py
proyecto_mlops/modeling/__init__.py
proyecto_mlops/utils/__init__.py
proyecto_mlops-0.1.6.dist-info/licenses/LICENSE
proyecto_mlops-0.1.6.dist-info/METADATA
proyecto_mlops-0.1.6.dist-info/WHEEL
proyecto_mlops-0.1.6.dist-info/entry_points.txt
proyecto_mlops-0.1.6.dist-info/top_level.txt
proyecto_mlops-0.1.6.dist-info/RECORD
