Metadata-Version: 2.4
Name: proyecto-mlops
Version: 0.1.6
Summary: MLOps Pipeline para Clasificación de Documentos en Español
Home-page: https://github.com/angelcast2002/PROYECTO-MLOPS
Author: Angel Castillo
Author-email: Angel Castillo <angelcast2002@gmail.com>
License: MIT
Project-URL: Homepage, https://github.com/angelcast2002/PROYECTO-MLOPS
Project-URL: Documentation, https://github.com/angelcast2002/PROYECTO-MLOPS/wiki
Project-URL: Repository, https://github.com/angelcast2002/PROYECTO-MLOPS
Project-URL: Issues, https://github.com/angelcast2002/PROYECTO-MLOPS/issues
Keywords: mlops,machine-learning,nlp,spanish,crisp-dm
Classifier: Programming Language :: Python :: 3
Classifier: Programming Language :: Python :: 3.8
Classifier: Programming Language :: Python :: 3.9
Classifier: Programming Language :: Python :: 3.10
Classifier: Programming Language :: Python :: 3.11
Classifier: License :: OSI Approved :: MIT License
Classifier: Operating System :: OS Independent
Classifier: Development Status :: 3 - Alpha
Classifier: Intended Audience :: Developers
Classifier: Topic :: Scientific/Engineering :: Artificial Intelligence
Requires-Python: >=3.8
License-File: LICENSE
Requires-Dist: pandas>=2.0.0
Requires-Dist: numpy>=1.20.0
Requires-Dist: scikit-learn>=1.0.0
Requires-Dist: nltk>=3.8
Requires-Dist: gensim>=4.0.0
Requires-Dist: spacy>=3.0.0
Requires-Dist: typer[all]>=0.9.0
Requires-Dist: pyyaml>=6.0
Requires-Dist: joblib>=1.2.0
Provides-Extra: dev
Requires-Dist: pytest>=7.0.0; extra == "dev"
Requires-Dist: pytest-cov>=3.0.0; extra == "dev"
Requires-Dist: black>=22.0.0; extra == "dev"
Requires-Dist: isort>=5.11.0; extra == "dev"
Requires-Dist: flake8>=4.0.0; extra == "dev"
Requires-Dist: mypy>=0.950; extra == "dev"
Requires-Dist: pylint>=2.13.0; extra == "dev"
Provides-Extra: docker
Requires-Dist: gunicorn>=20.0.0; extra == "docker"
Requires-Dist: uvicorn>=0.17.0; extra == "docker"
Dynamic: author
Dynamic: home-page
Dynamic: license-file
Dynamic: requires-python
